[
  {
    "id": "1",
    "title": "Маргарита",
    "vendor_code": "111",
    "price": 400,
    "img": "margarita.png"
  },
  {
    "id": "2",
    "title": "Пепперони",
    "vendor_code": "222",
    "price": 500,
    "img": "pepperoni.png"
  },
  {
    "id": "3",
    "title": "Неаполитанская",
    "vendor_code": "333",
    "price": 550,
    "img": "neapolitanskaya.png"
  },
  {
    "id": "4",
    "title": "Гавайская",
    "vendor_code": "444",
    "price": 500,
    "img": "gavayskaya.png"
  },
  {
    "id": "5",
    "title": "Четыре сезона",
    "vendor_code": "555",
    "price": 600,
    "img": "four_season.png"
  },
  {
    "id": "6",
    "title": "Четыре сыра",
    "vendor_code": "666",
    "price": 550,
    "img": "four_chesee.png"
  },
  {
    "id": "7",
    "title": "Диабло",
    "vendor_code": "7",
    "price": 600,
    "img": "diablo.png"
  },
  {
    "id": "8",
    "title": "Баварская",
    "vendor_code": "888",
    "price": 400,
    "img": "bavarskaya.png"
  },
  {
    "id": "9",
    "title": "Вегетерианская",
    "vendor_code": "999",
    "price": 400,
    "img": "vegeterian.png"
  },
  {
    "id": "10",
    "title": "Ветчина и грибы",
    "vendor_code": "000",
    "price": 450,
    "img": "ham_and_mushrooms.png"
  }
]